toika_loom_server/__init__.py
toika_loom_server/favicon-32x32.png
toika_loom_server/loom_server.py
toika_loom_server/main.py
toika_loom_server/mock_loom.py
toika_loom_server/py.typed
toika_loom_server/utils.py
toika_loom_server/version.py
toika_loom_server-0.10.1.dist-info/licenses/LICENSE.txt
toika_loom_server-0.10.1.dist-info/METADATA
toika_loom_server-0.10.1.dist-info/WHEEL
toika_loom_server-0.10.1.dist-info/entry_points.txt
toika_loom_server-0.10.1.dist-info/top_level.txt
toika_loom_server-0.10.1.dist-info/RECORD
